hostip_client/__init__.py
hostip_client/ip.py
hostip_client-1.0.4.dist-info/METADATA
hostip_client-1.0.4.dist-info/WHEEL
hostip_client-1.0.4.dist-info/licenses/LICENSE
hostip_client-1.0.4.dist-info/RECORD
