Metadata-Version: 2.3
Name: hostip_client
Version: 1.0.4
Summary: A small hostip API client
Project-URL: Homepage, https://github.com/rh363/hostip_client
Project-URL: Issues, https://github.com/rh363/hostip_client/issues
Author-email: Alex Massaroni <alex.m@seeweb.it>
Classifier: License :: OSI Approved :: The Unlicense (Unlicense)
Classifier: Operating System :: OS Independent
Classifier: Programming Language :: Python :: 3
Requires-Python: >=3.0
Requires-Dist: requests>=2.32.3
